Doc2Map.py
doc2map-1.0.3.dist-info/LICENSE
doc2map-1.0.3.dist-info/METADATA
doc2map-1.0.3.dist-info/WHEEL
doc2map-1.0.3.dist-info/top_level.txt
doc2map-1.0.3.dist-info/RECORD
